MhcVizPipe/__init__.py
MhcVizPipe/cli.py
MhcVizPipe/gui.py
MhcVizPipe/mhcvizpipe_defaults.config
MhcVizPipe/mhcvizpipe_standalone_defaults.config
MhcVizPipe/parameters.py
MhcVizPipe/Reporting/__init__.py
MhcVizPipe/Reporting/report.py
MhcVizPipe/Tools/__init__.py
MhcVizPipe/Tools/cl_tools.py
MhcVizPipe/Tools/jobs.py
MhcVizPipe/Tools/netmhcpan_helper.py
MhcVizPipe/Tools/plotly_venn.py
MhcVizPipe/Tools/utils.py
MhcVizPipe/assets/bootstrap_4.5.0.min.css
MhcVizPipe/assets/bootstrap_4.5.0.min.js
MhcVizPipe/assets/class_II_alleles.txt
MhcVizPipe/assets/class_I_alleles.txt
MhcVizPipe/assets/dash_basic.css
MhcVizPipe/assets/gui_styles.css
MhcVizPipe/assets/logo_CARONLAB_horizontal.jpg
MhcVizPipe/assets/report_style.css
MhcVizPipe-0.7.11.dist-info/LICENSE
MhcVizPipe-0.7.11.dist-info/METADATA
MhcVizPipe-0.7.11.dist-info/WHEEL
MhcVizPipe-0.7.11.dist-info/top_level.txt
MhcVizPipe-0.7.11.dist-info/RECORD
